<annotation>
	<folder>downloaded</folder>
	<filename>155.jpg</filename>
	<path>C:\Users\Bijnis\OneDrive\Desktop\downloaded\155.jpg</path>
	<source>
		<database>Unknown</database>
	</source>
	<size>
		<width>3376</width>
		<height>5565</height>
		<depth>3</depth>
	</size>
	<segmented>0</segmented>
	<object>
		<name>Footwear</name>
		<pose>Unspecified</pose>
		<truncated>0</truncated>
		<difficult>0</difficult>
		<bndbox>
			<xmin>1010</xmin>
			<ymin>4355</ymin>
			<xmax>1656</xmax>
			<ymax>5100</ymax>
		</bndbox>
	</object>
	<object>
		<name>Footwear</name>
		<pose>Unspecified</pose>
		<truncated>0</truncated>
		<difficult>0</difficult>
		<bndbox>
			<xmin>1619</xmin>
			<ymin>4664</ymin>
			<xmax>2183</xmax>
			<ymax>5173</ymax>
		</bndbox>
	</object>
</annotation>
