<annotation>
	<folder>downloaded</folder>
	<filename>166.jpg</filename>
	<path>C:\Users\Bijnis\OneDrive\Desktop\downloaded\166.jpg</path>
	<source>
		<database>Unknown</database>
	</source>
	<size>
		<width>4480</width>
		<height>6720</height>
		<depth>3</depth>
	</size>
	<segmented>0</segmented>
	<object>
		<name>Footwear</name>
		<pose>Unspecified</pose>
		<truncated>0</truncated>
		<difficult>0</difficult>
		<bndbox>
			<xmin>1067</xmin>
			<ymin>3138</ymin>
			<xmax>4034</xmax>
			<ymax>5415</ymax>
		</bndbox>
	</object>
</annotation>
